korean_news_scraper/__init__.py
korean_news_scraper/extract_article_content.py
korean_news_scraper/save_article_links.py
korean_news_scraper/scroll_down_page.py
korean_news_scraper-0.1.5.dist-info/LICENSE
korean_news_scraper-0.1.5.dist-info/METADATA
korean_news_scraper-0.1.5.dist-info/WHEEL
korean_news_scraper-0.1.5.dist-info/top_level.txt
korean_news_scraper-0.1.5.dist-info/RECORD
